pygrabshot/__init__.py
pygrabshot/__main__.py
pygrabshot/base.py
pygrabshot/darwin.py
pygrabshot/exception.py
pygrabshot/factory.py
pygrabshot/linux.py
pygrabshot/models.py
pygrabshot/screenshot.py
pygrabshot/test.py
pygrabshot/tools.py
pygrabshot/windows.py
pygrabshot-1.0.3.dist-info/LICENSE.txt
pygrabshot-1.0.3.dist-info/METADATA
pygrabshot-1.0.3.dist-info/WHEEL
pygrabshot-1.0.3.dist-info/top_level.txt
pygrabshot-1.0.3.dist-info/RECORD
